xmlduckdb/__init__.py
xmlduckdb/open_xml_extractor.py
xmlduckdb-0.1.0.dist-info/METADATA
xmlduckdb-0.1.0.dist-info/WHEEL
xmlduckdb-0.1.0.dist-info/RECORD
