Metadata-Version: 2.1
Name: xmlduckdb
Version: 0.1.0
Summary: A package for processing XML with DuckDB.
License: MIT
Author: Isaac Moore
Author-email: isaaacmooreuky@gmail.com
Requires-Python: >=3.6,<4.0
Classifier: License :: OSI Approved :: MIT License
Classifier: Programming Language :: Python :: 3
Classifier: Programming Language :: Python :: 3.6
Classifier: Programming Language :: Python :: 3.7
Classifier: Programming Language :: Python :: 3.8
Classifier: Programming Language :: Python :: 3.9
Classifier: Programming Language :: Python :: 3.10
Classifier: Programming Language :: Python :: 3.11
Classifier: Programming Language :: Python :: 3.12
Requires-Dist: duckdb (>=1.0.0,<2.0.0)
Requires-Dist: lxml (>=5.3.0,<6.0.0)
